rtspntf/__init__.py
rtspntf/cli.py
rtspntf/const.py
rtspntf/main.py
rtspntf/version.py
rtspntf-0.1.3.dist-info/METADATA
rtspntf-0.1.3.dist-info/WHEEL
rtspntf-0.1.3.dist-info/entry_points.txt
rtspntf-0.1.3.dist-info/RECORD
