Metadata-Version: 2.1
Name: rtspntf
Version: 0.1.3
Summary: Motion detection from RTSP image stream (intended for intercom image)
Author: Kyosuke Miyamura
Author-email: ask@386.jp
Requires-Python: >=3.9,<4.0
Classifier: Programming Language :: Python :: 3
Classifier: Programming Language :: Python :: 3.9
Classifier: Programming Language :: Python :: 3.10
Classifier: Programming Language :: Python :: 3.11
Classifier: Programming Language :: Python :: 3.12
Requires-Dist: numpy (>=1.26.4,<2.0.0)
Requires-Dist: opencv-python (>=4.9.0.80,<5.0.0.0)
Requires-Dist: requests (>=2.31.0,<3.0.0)
Requires-Dist: rtsp (>=1.1.12,<2.0.0)
